{
  "title": "Home Assistant Email Bridge",
  "config": {
    "step": {
      "user": {
        "title": "Set up Home Assistant Email Bridge",
        "description": "Create a local webhook receiver for fake email notifications. Recipient names map to Home Assistant notify services.",
        "data": {
          "webhook_id": "Webhook ID",
          "default_notify_service": "Default notify service",
          "recipients": "Recipients JSON"
        }
      }
    },
    "error": {
      "invalid_recipients": "Recipients must be valid JSON. Each recipient needs notify_service or notify_services."
    },
    "abort": {
      "already_configured": "Home Assistant Email Bridge is already configured."
    }
  },
  "options": {
    "step": {
      "init": {
        "title": "Home Assistant Email Bridge options",
        "description": "Manage fake email recipients and their Home Assistant notify services.",
        "menu_options": {
          "view_addresses": "View local email addresses",
          "add_recipient": "Add or update recipient",
          "edit_recipient": "Edit recipient",
          "remove_recipient": "Remove recipient",
          "send_test": "Send test notification",
          "edit_json": "Edit raw JSON"
        }
      },
      "view_addresses": {
        "title": "Local email addresses",
        "description": "Use these settings for a server-based device or service on the Home Assistant host:\n\nSMTP server: {smtp_host}\nSMTP port: {smtp_port}\nSecurity: none\nAuthentication: none\n\nConfigured recipients:\n{addresses}"
      },
      "add_recipient": {
        "title": "Add or update recipient",
        "description": "The recipient name is the fake email local part, such as dad in dad@ha-notify.local. The notify service list is populated from active Home Assistant notify services.",
        "data": {
          "recipient": "Recipient name",
          "emails": "Fake email aliases",
          "notify_service": "Notify service",
          "fallback_services": "Fallback services",
          "title_prefix": "Title prefix"
        }
      },
      "edit_recipient": {
        "title": "Edit recipient",
        "description": "Choose one configured recipient to edit.",
        "data": {
          "recipient": "Recipient"
        }
      },
      "edit_selected_recipient": {
        "title": "Edit {recipient}",
        "description": "Update this recipient's fake email aliases and Home Assistant notification targets.",
        "data": {
          "emails": "Fake email aliases",
          "notify_service": "Notify service",
          "fallback_services": "Fallback services",
          "title_prefix": "Title prefix"
        }
      },
      "remove_recipient": {
        "title": "Remove recipient",
        "description": "Remove a fake email recipient mapping.",
        "data": {
          "recipient": "Recipient"
        }
      },
      "send_test": {
        "title": "Send test notification",
        "description": "Send a fully formed test message through the same dispatch path used by the SMTP bridge.",
        "data": {
          "recipient": "Recipient",
          "recipient_address": "Destination email address",
          "source": "Source",
          "from_address": "From address",
          "severity": "Severity",
          "subject": "Subject",
          "message": "Message"
        }
      },
      "edit_json": {
        "title": "Edit raw JSON",
        "description": "Update recipient mappings as JSON.",
        "data": {
          "default_notify_service": "Default notify service",
          "recipients": "Recipients JSON"
        }
      }
    },
    "error": {
      "invalid_recipients": "Recipients must be valid JSON. Each recipient needs notify_service or notify_services.",
      "invalid_notify_services": "Fallback services must be comma-separated service names such as notify.mobile_app_dads_iphone,persistent_notification.create.",
      "no_recipients": "There are no recipients configured.",
      "no_notify_service": "No configured notify service was available for this recipient.",
      "required": "This field is required."
    }
  },
  "entity": {
    "sensor": {
      "recipient": {
        "name": "{recipient}"
      }
    }
  }
}
